matrix_bot_lib/__init__.py
matrix_bot_lib/botlib.py
matrix_bot_lib/models.py
matrix_bot_lib-0.1.8.dist-info/LICENSE
matrix_bot_lib-0.1.8.dist-info/METADATA
matrix_bot_lib-0.1.8.dist-info/WHEEL
matrix_bot_lib-0.1.8.dist-info/RECORD
