Metadata-Version: 2.1
Name: matrix-bot-lib
Version: 0.1.8
Summary: Super early lib for interacting with Matrix
Author: Nicolai Søborg
Author-email: git@xn--sb-lka.org
Requires-Python: >=3.10,<4.0
Classifier: Programming Language :: Python :: 3
Classifier: Programming Language :: Python :: 3.10
Classifier: Programming Language :: Python :: 3.11
Classifier: Programming Language :: Python :: 3.12
Classifier: Programming Language :: Python :: 3.13
Requires-Dist: httpx[http2] (>=0.27.0,<0.28.0)
Requires-Dist: result (>=0.17.0,<0.18.0)
